openbb_ai/__init__.py
openbb_ai/helpers.py
openbb_ai/models.py
openbb_ai/py.typed
openbb_ai/testing.py
openbb_ai-1.8.6.dist-info/LICENSE
openbb_ai-1.8.6.dist-info/METADATA
openbb_ai-1.8.6.dist-info/WHEEL
openbb_ai-1.8.6.dist-info/RECORD
