Metadata-Version: 2.3
Name: openbb-ai
Version: 1.8.6
Summary: An SDK for building agents compatible with OpenBB Workspace
Author: OpenBB Team
Author-email: hello@openbb.finance
Requires-Python: >=3.10
Classifier: Programming Language :: Python :: 3
Classifier: Programming Language :: Python :: 3.10
Classifier: Programming Language :: Python :: 3.11
Classifier: Programming Language :: Python :: 3.12
Classifier: Programming Language :: Python :: 3.13
Requires-Dist: pydantic (>=2.12.0,<3.0.0)
Requires-Dist: xxhash (>=3.5.0,<4.0.0)
